todo_or_not/__init__.py
todo_or_not/localize.py
todo_or_not/parser.out
todo_or_not/parsetab.py
todo_or_not/todo_app.py
todo_or_not/todo_check.py
todo_or_not/todo_grammar.py
todo_or_not/todo_hit.py
todo_or_not/utility.py
todo_or_not-0.14.7.dist-info/LICENSE
todo_or_not-0.14.7.dist-info/METADATA
todo_or_not-0.14.7.dist-info/WHEEL
todo_or_not-0.14.7.dist-info/entry_points.txt
todo_or_not-0.14.7.dist-info/RECORD
