Metadata-Version: 2.1
Name: todo-or-not
Version: 0.14.7
Summary: todoon integrates the TODOs in your codebase with your GitHub repository
Home-page: https://github.com/apps/todo-or-not
License: GPL-3.0-only
Keywords: todo,github
Author: TrentonYo
Author-email: trentonyo@gmail.com
Requires-Python: >=3.11,<4.0
Classifier: License :: OSI Approved :: GNU General Public License v3 (GPLv3)
Classifier: Programming Language :: Python :: 3
Classifier: Programming Language :: Python :: 3.11
Classifier: Programming Language :: Python :: 3.12
Classifier: Programming Language :: Python :: 3.13
Requires-Dist: ply (>=3.11,<4.0)
Requires-Dist: tqdm (>=4.66.4,<5.0.0)
Requires-Dist: typer (>=0.12.3,<0.13.0)
Requires-Dist: typing-extensions (>=4.10.0,<5.0.0)
Project-URL: Documentation, https://github.com/Start-Out/todo-or-not/wiki
Project-URL: Repository, https://github.com/Start-Out/todo-or-not
